my_cookiecutter_demo/__init__.py
my_cookiecutter_demo/common.py
my_cookiecutter_demo/my_cookiecutter_demo.py
my_cookiecutter_demo-0.0.2.dist-info/LICENSE
my_cookiecutter_demo-0.0.2.dist-info/METADATA
my_cookiecutter_demo-0.0.2.dist-info/WHEEL
my_cookiecutter_demo-0.0.2.dist-info/entry_points.txt
my_cookiecutter_demo-0.0.2.dist-info/top_level.txt
my_cookiecutter_demo-0.0.2.dist-info/RECORD
